{"_path":"/examples","_dir":"","_draft":false,"_partial":false,"_locale":"","title":"Examples","description":"Run the sample apps in this repo to see each integration in action.","body":{"type":"root","children":[{"type":"element","tag":"h1","props":{"id":"examples"},"children":[{"type":"text","value":"🧪 Examples"}]},{"type":"element","tag":"p","props":{},"children":[{"type":"text","value":"Every package in this monorepo has a matching example under "},{"type":"element","tag":"code","props":{"className":[]},"children":[{"type":"text","value":"examples/"}]},{"type":"text","value":". Each example is wired to the local workspace packages ("},{"type":"element","tag":"code","props":{"className":[]},"children":[{"type":"text","value":"workspace:*"}]},{"type":"text","value":"), so you can make changes and see them reflected immediately."}]},{"type":"element","tag":"blockquote","props":{},"children":[{"type":"element","tag":"p","props":{},"children":[{"type":"text","value":"Requirements: Node 24+, pnpm 9+, "},{"type":"element","tag":"code","props":{"className":[]},"children":[{"type":"text","value":"pnpm install"}]},{"type":"text","value":" run at the repo root."}]}]},{"type":"element","tag":"h2","props":{"id":"vite-spa"},"children":[{"type":"text","value":"Vite SPA"}]},{"type":"element","tag":"ul","props":{},"children":[{"type":"element","tag":"li","props":{},"children":[{"type":"text","value":"Path: "},{"type":"element","tag":"code","props":{"className":[]},"children":[{"type":"text","value":"examples/vite-app"}]}]},{"type":"element","tag":"li","props":{},"children":[{"type":"text","value":"Command: "},{"type":"element","tag":"code","props":{"className":[]},"children":[{"type":"text","value":"pnpm --filter example-vite dev"}]},{"type":"text","value":" or "},{"type":"element","tag":"code","props":{"className":[]},"children":[{"type":"text","value":"pnpm --filter example-vite build"}]}]},{"type":"element","tag":"li","props":{},"children":[{"type":"text","value":"Highlights:\n"},{"type":"element","tag":"ul","props":{},"children":[{"type":"element","tag":"li","props":{},"children":[{"type":"text","value":"Enables source maps ("},{"type":"element","tag":"code","props":{"className":[]},"children":[{"type":"text","value":"build.sourcemap = true"}]},{"type":"text","value":") so the upcoming Vite parser can extract source-file insights."}]},{"type":"element","tag":"li","props":{},"children":[{"type":"text","value":"Turns on dashboard generation ("},{"type":"element","tag":"code","props":{"className":[]},"children":[{"type":"text","value":"bundle-report/index.html"}]},{"type":"text","value":") for quick inspections without Git storage."}]}]}]}]},{"type":"element","tag":"p","props":{},"children":[{"type":"text","value":"Config snippet ("},{"type":"element","tag":"code","props":{"className":[]},"children":[{"type":"text","value":"examples/vite-app/vite.config.ts"}]},{"type":"text","value":"):"}]},{"type":"element","tag":"pre","props":{"className":"language-ts shiki shiki-themes github-dark","code":"bundleWatch({\n  generateDashboard: true,\n  compareAgainst: 'main',\n  analyzeSourceMaps: true,\n});\n","language":"ts","meta":"","style":""},"children":[{"type":"element","tag":"code","props":{"__ignoreMap":""},"children":[{"type":"element","tag":"span","props":{"class":"line","line":1},"children":[{"type":"element","tag":"span","props":{"style":"--shiki-default:#B392F0"},"children":[{"type":"text","value":"bundleWatch"}]},{"type":"element","tag":"span","props":{"style":"--shiki-default:#E1E4E8"},"children":[{"type":"text","value":"({\n"}]}]},{"type":"element","tag":"span","props":{"class":"line","line":2},"children":[{"type":"element","tag":"span","props":{"style":"--shiki-default:#E1E4E8"},"children":[{"type":"text","value":"  generateDashboard: "}]},{"type":"element","tag":"span","props":{"style":"--shiki-default:#79B8FF"},"children":[{"type":"text","value":"true"}]},{"type":"element","tag":"span","props":{"style":"--shiki-default:#E1E4E8"},"children":[{"type":"text","value":",\n"}]}]},{"type":"element","tag":"span","props":{"class":"line","line":3},"children":[{"type":"element","tag":"span","props":{"style":"--shiki-default:#E1E4E8"},"children":[{"type":"text","value":"  compareAgainst: "}]},{"type":"element","tag":"span","props":{"style":"--shiki-default:#9ECBFF"},"children":[{"type":"text","value":"'main'"}]},{"type":"element","tag":"span","props":{"style":"--shiki-default:#E1E4E8"},"children":[{"type":"text","value":",\n"}]}]},{"type":"element","tag":"span","props":{"class":"line","line":4},"children":[{"type":"element","tag":"span","props":{"style":"--shiki-default:#E1E4E8"},"children":[{"type":"text","value":"  analyzeSourceMaps: "}]},{"type":"element","tag":"span","props":{"style":"--shiki-default:#79B8FF"},"children":[{"type":"text","value":"true"}]},{"type":"element","tag":"span","props":{"style":"--shiki-default:#E1E4E8"},"children":[{"type":"text","value":",\n"}]}]},{"type":"element","tag":"span","props":{"class":"line","line":5},"children":[{"type":"element","tag":"span","props":{"style":"--shiki-default:#E1E4E8"},"children":[{"type":"text","value":"});\n"}]}]}]}]},{"type":"element","tag":"h2","props":{"id":"webpack-react-app"},"children":[{"type":"text","value":"Webpack React app"}]},{"type":"element","tag":"ul","props":{},"children":[{"type":"element","tag":"li","props":{},"children":[{"type":"text","value":"Path: "},{"type":"element","tag":"code","props":{"className":[]},"children":[{"type":"text","value":"examples/webpack-app"}]}]},{"type":"element","tag":"li","props":{},"children":[{"type":"text","value":"Command: "},{"type":"element","tag":"code","props":{"className":[]},"children":[{"type":"text","value":"pnpm --filter example-webpack-app build"}]}]},{"type":"element","tag":"li","props":{},"children":[{"type":"text","value":"Uses the parser-powered Webpack plugin with module extraction, dependency graphing, and optimization recommendations enabled."}]},{"type":"element","tag":"li","props":{},"children":[{"type":"text","value":"Generates a dashboard at "},{"type":"element","tag":"code","props":{"className":[]},"children":[{"type":"text","value":"examples/webpack-app/bundle-report/index.html"}]},{"type":"text","value":" that includes module/dependency tables."}]}]},{"type":"element","tag":"h2","props":{"id":"nextjs-client-bundle"},"children":[{"type":"text","value":"Next.js client bundle"}]},{"type":"element","tag":"ul","props":{},"children":[{"type":"element","tag":"li","props":{},"children":[{"type":"text","value":"Path: "},{"type":"element","tag":"code","props":{"className":[]},"children":[{"type":"text","value":"examples/next-app"}]}]},{"type":"element","tag":"li","props":{},"children":[{"type":"text","value":"Command: "},{"type":"element","tag":"code","props":{"className":[]},"children":[{"type":"text","value":"pnpm --filter example-next-app build"}]}]},{"type":"element","tag":"li","props":{},"children":[{"type":"text","value":"Demonstrates adding "},{"type":"element","tag":"code","props":{"className":[]},"children":[{"type":"text","value":"BundleWatchPlugin"}]},{"type":"text","value":" inside "},{"type":"element","tag":"code","props":{"className":[]},"children":[{"type":"text","value":"next.config.js"}]},{"type":"text","value":" so only the client build triggers the analysis. Dashboards land in "},{"type":"element","tag":"code","props":{"className":[]},"children":[{"type":"text","value":"./bundle-report"}]},{"type":"text","value":"."}]},{"type":"element","tag":"li","props":{},"children":[{"type":"text","value":"Good reference for custom Webpack hooks (e.g., skipping server bundles)."}]}]},{"type":"element","tag":"h2","props":{"id":"nuxt-vite-app"},"children":[{"type":"text","value":"Nuxt (Vite) app"}]},{"type":"element","tag":"ul","props":{},"children":[{"type":"element","tag":"li","props":{},"children":[{"type":"text","value":"Path: "},{"type":"element","tag":"code","props":{"className":[]},"children":[{"type":"text","value":"examples/nuxt-app"}]}]},{"type":"element","tag":"li","props":{},"children":[{"type":"text","value":"Command: "},{"type":"element","tag":"code","props":{"className":[]},"children":[{"type":"text","value":"pnpm --filter example-nuxt-app build"}]}]},{"type":"element","tag":"li","props":{},"children":[{"type":"text","value":"Shows how to inject the Vite plugin via "},{"type":"element","tag":"code","props":{"className":[]},"children":[{"type":"text","value":"nuxt.config.ts → vite.plugins"}]},{"type":"text","value":"."}]},{"type":"element","tag":"li","props":{},"children":[{"type":"text","value":"Useful for testing SSR/SSG projects with the Vite integration."}]}]},{"type":"element","tag":"h2","props":{"id":"sveltekit"},"children":[{"type":"text","value":"SvelteKit"}]},{"type":"element","tag":"ul","props":{},"children":[{"type":"element","tag":"li","props":{},"children":[{"type":"text","value":"Path: "},{"type":"element","tag":"code","props":{"className":[]},"children":[{"type":"text","value":"examples/sveltekit-app"}]}]},{"type":"element","tag":"li","props":{},"children":[{"type":"text","value":"Command: "},{"type":"element","tag":"code","props":{"className":[]},"children":[{"type":"text","value":"pnpm --filter example-sveltekit-app build"}]}]},{"type":"element","tag":"li","props":{},"children":[{"type":"text","value":"Adds BundleWatch to "},{"type":"element","tag":"code","props":{"className":[]},"children":[{"type":"text","value":"kit.vite.plugins"}]},{"type":"text","value":" so it runs during "},{"type":"element","tag":"code","props":{"className":[]},"children":[{"type":"text","value":"svelte-kit build"}]},{"type":"text","value":"."}]}]},{"type":"element","tag":"h2","props":{"id":"solidstart"},"children":[{"type":"text","value":"SolidStart"}]},{"type":"element","tag":"ul","props":{},"children":[{"type":"element","tag":"li","props":{},"children":[{"type":"text","value":"Path: "},{"type":"element","tag":"code","props":{"className":[]},"children":[{"type":"text","value":"examples/solidstart-app"}]}]},{"type":"element","tag":"li","props":{},"children":[{"type":"text","value":"Command: "},{"type":"element","tag":"code","props":{"className":[]},"children":[{"type":"text","value":"pnpm --filter example-solidstart-app build"}]}]},{"type":"element","tag":"li","props":{},"children":[{"type":"text","value":"Wraps the plugin inside "},{"type":"element","tag":"code","props":{"className":[]},"children":[{"type":"text","value":"defineConfig({ vite: { plugins: [...] } })"}]},{"type":"text","value":", mirroring the instructions in "},{"type":"element","tag":"a","props":{"href":"./framework-recipes"},"children":[{"type":"text","value":"Framework Recipes"}]},{"type":"text","value":"."}]}]},{"type":"element","tag":"hr","props":{},"children":[]},{"type":"element","tag":"h3","props":{"id":"tips"},"children":[{"type":"text","value":"Tips"}]},{"type":"element","tag":"ul","props":{},"children":[{"type":"element","tag":"li","props":{},"children":[{"type":"text","value":"Clean up dashboards by running "},{"type":"element","tag":"code","props":{"className":[]},"children":[{"type":"text","value":"rm -rf bundle-report"}]},{"type":"text","value":" inside each example directory."}]},{"type":"element","tag":"li","props":{},"children":[{"type":"text","value":"Use "},{"type":"element","tag":"code","props":{"className":[]},"children":[{"type":"text","value":"pnpm --filter <example> exec tree -L 2 bundle-report"}]},{"type":"text","value":" to inspect generated assets in CI logs."}]},{"type":"element","tag":"li","props":{},"children":[{"type":"text","value":"Keep examples up to date when you change plugin options—this page should always mirror reality."}]}]},{"type":"element","tag":"style","props":{},"children":[{"type":"text","value":"html .default .shiki span {color: var(--shiki-default);background: var(--shiki-default-bg);font-style: var(--shiki-default-font-style);font-weight: var(--shiki-default-font-weight);text-decoration: var(--shiki-default-text-decoration);}html .shiki span {color: var(--shiki-default);background: var(--shiki-default-bg);font-style: var(--shiki-default-font-style);font-weight: var(--shiki-default-font-weight);text-decoration: var(--shiki-default-text-decoration);}"}]}],"toc":{"title":"","searchDepth":2,"depth":2,"links":[{"id":"vite-spa","depth":2,"text":"Vite SPA"},{"id":"webpack-react-app","depth":2,"text":"Webpack React app"},{"id":"nextjs-client-bundle","depth":2,"text":"Next.js client bundle"},{"id":"nuxt-vite-app","depth":2,"text":"Nuxt (Vite) app"},{"id":"sveltekit","depth":2,"text":"SvelteKit"},{"id":"solidstart","depth":2,"text":"SolidStart","children":[{"id":"tips","depth":3,"text":"Tips"}]}]}},"_type":"markdown","_id":"content:examples.md","_source":"content","_file":"examples.md","_stem":"examples","_extension":"md"}